mcp_server_gac/__init__.py
mcp_server_gac/server.py
mcp_server_gac-0.0.3.dist-info/METADATA
mcp_server_gac-0.0.3.dist-info/WHEEL
mcp_server_gac-0.0.3.dist-info/entry_points.txt
mcp_server_gac-0.0.3.dist-info/RECORD
